{"dataIncorporacao":"2020-04-08T00:00:00.000Z","prefixo":"GL600","vidaUtil":120,"saldoVidaUtil":87,"placa":"BDW2J38","anoFabricacao":2019,"chassiNumero":"M. BENZ","chassiMarca":"9BM382154LB168068","chassiModelo":"O500MA","carroceriaFabricante":"MARCOPOLO","carroceriaModelo":"TORINO","categoria":"LINHA DIRETA","elevador":false,"areaSalao":19.86,"lotacaoSentados":35,"lotacaoEmPe":119,"lotacaoTotal":154,"cor":"CINZA","tipoVeiculo":"ARTICULADO","empresa":"SORRISO","historico":{"placa":"AUV3526 => BDW2J38","carroceria":"MARCOPOLO/SENIOR => MARCOPOLO/TORINO","categoria":"PROGRAMA ACESSO => LINHA DIRETA","lotacao":"(Sentados: 6, Em pé: 22 e Total: 28) => (Sentados: 35, Em pé: 119 e Total: 154)","cor":"DOURADA => CINZA","tipoVeiculo":"MICRO => ARTICULADO","empresa":"SAO JOSE => SORRISO"},"observacoes":"Mudou de Empresa (SAO JOSE), Mudou de Placa (AUV3526), Reencarroçado (MARCOPOLO/SENIOR), Mudou a Lotação (Sentados: 6 e Total: 28), Mudou de Tipo de Veículo (MICRO)"}