{"dataIncorporacao":"2020-07-30T00:00:00.000Z","prefixo":"EB609","vidaUtil":120,"saldoVidaUtil":116,"placa":"BED8B93","anoFabricacao":2019,"chassiNumero":"9BM382154MB174141","chassiMarca":"MERCEDES","chassiModelo":"O500 MA","carroceriaFabricante":"MARCOPOLO","carroceriaModelo":"TORINO","categoria":"INTERBAIRROS","elevador":true,"areaSalao":18.1,"lotacaoSentados":33,"lotacaoEmPe":108,"lotacaoTotal":141,"cor":"VERDE","tipoVeiculo":"ARTICULADO","empresa":"SAO JOSE","historico":{"placa":null,"carroceria":null,"categoria":null,"lotacao":null,"cor":"null => VERDE","tipoVeiculo":null,"empresa":null},"observacoes":"Repintado (null)"}