{"dataIncorporacao":"2012-03-05T00:00:00.000Z","prefixo":"HE710","vidaUtil":120,"saldoVidaUtil":15,"placa":"AUV9308","anoFabricacao":2011,"chassiNumero":"9BVR9F826BE380998","chassiMarca":"VOLVO","chassiModelo":"B 12M","carroceriaFabricante":"NEOBUS","carroceriaModelo":"MEGA BRT","categoria":"EXPRESSO","elevador":false,"areaSalao":33.26,"lotacaoSentados":57,"lotacaoEmPe":199,"lotacaoTotal":256,"cor":"VERMELHA","tipoVeiculo":"BIARTICULADO","empresa":"REDENTOR","historico":{"placa":null,"carroceria":null,"categoria":null,"lotacao":null,"cor":"null => VERMELHA","tipoVeiculo":null,"empresa":null},"observacoes":"Repintado (null)"}