{"dataIncorporacao":"2008-08-19T00:00:00.000Z","prefixo":"MR800","vidaUtil":120,"saldoVidaUtil":-69,"placa":"AQH7657","anoFabricacao":2008,"chassiNumero":"9BSK6X2A083627220","chassiMarca":"SCANIA","chassiModelo":"K94IA 6X2 2NB","carroceriaFabricante":"NIEL/BUSSCAR","carroceriaModelo":"URBANUSS","categoria":"LINHA DIRETA","elevador":false,"areaSalao":17.89,"lotacaoSentados":42,"lotacaoEmPe":107,"lotacaoTotal":149,"cor":"PRATA","tipoVeiculo":"ARTICULADO","empresa":"MERCES","historico":null,"observacoes":""}