{"dataIncorporacao":"2012-05-16T00:00:00.000Z","prefixo":"MP950","vidaUtil":120,"saldoVidaUtil":-22,"placa":"AUY2869","anoFabricacao":2011,"chassiNumero":"M. BENZ","chassiMarca":"9BM688277CB810908","chassiModelo":"LO915/48","carroceriaFabricante":"NEOBUS","carroceriaModelo":"THUNDER","categoria":"PROGRAMA ACESSO","elevador":true,"areaSalao":4.13,"lotacaoSentados":6,"lotacaoEmPe":24,"lotacaoTotal":30,"cor":"DOURADA","tipoVeiculo":"MICRO","empresa":"MERCES","historico":{"placa":null,"carroceria":"MARCOPOLO/SENIOR => NEOBUS/THUNDER","categoria":null,"lotacao":"(Sentados: 7, Em pé: 26 e Total: 33) => (Sentados: 6, Em pé: 24 e Total: 30)","cor":null,"tipoVeiculo":null,"empresa":"SORRISO => MERCES"},"observacoes":"Mudou de Empresa (SORRISO), Reencarroçado (MARCOPOLO/SENIOR), Mudou a Lotação (Sentados: 7 e Total: 33)"}